luke_test_project/__init__.py
luke_test_project/num.py
luke_test_project-0.1.5.dist-info/METADATA
luke_test_project-0.1.5.dist-info/WHEEL
luke_test_project-0.1.5.dist-info/RECORD
